RagTag-2.1.0.data/scripts/ragtag.py
RagTag-2.1.0.data/scripts/ragtag_agp2fa.py
RagTag-2.1.0.data/scripts/ragtag_agpcheck.py
RagTag-2.1.0.data/scripts/ragtag_asmstats.py
RagTag-2.1.0.data/scripts/ragtag_break_query.py
RagTag-2.1.0.data/scripts/ragtag_correct.py
RagTag-2.1.0.data/scripts/ragtag_create_links.py
RagTag-2.1.0.data/scripts/ragtag_delta2paf.py
RagTag-2.1.0.data/scripts/ragtag_merge.py
RagTag-2.1.0.data/scripts/ragtag_paf2delta.py
RagTag-2.1.0.data/scripts/ragtag_patch.py
RagTag-2.1.0.data/scripts/ragtag_rename.py
RagTag-2.1.0.data/scripts/ragtag_scaffold.py
RagTag-2.1.0.data/scripts/ragtag_splitasm.py
RagTag-2.1.0.data/scripts/ragtag_stats.py
RagTag-2.1.0.data/scripts/ragtag_update_gff.py
RagTag-2.1.0.data/scripts/setup.py
ragtag_utilities/AGPFile.py
ragtag_utilities/Aligner.py
ragtag_utilities/AlignmentReader.py
ragtag_utilities/ContigAlignment.py
ragtag_utilities/RestrictionFragmentMap.py
ragtag_utilities/ScaffoldGraph.py
ragtag_utilities/__init__.py
ragtag_utilities/utilities.py
RagTag-2.1.0.dist-info/LICENSE
RagTag-2.1.0.dist-info/METADATA
RagTag-2.1.0.dist-info/WHEEL
RagTag-2.1.0.dist-info/top_level.txt
RagTag-2.1.0.dist-info/zip-safe
RagTag-2.1.0.dist-info/RECORD
