Metadata-Version: 2.1
Name: RagTag
Version: 2.1.0
Summary: Fast reference-guided genome assembly scaffolding
Home-page: https://github.com/malonge/RagTag
Author: Michael Alonge
Author-email: malonge11@gmail.com
License: MIT
Platform: UNKNOWN
Classifier: Programming Language :: Python :: 3
Classifier: License :: OSI Approved :: MIT License
Requires-Python: >=3.6
License-File: LICENSE
Requires-Dist: intervaltree
Requires-Dist: numpy
Requires-Dist: pysam
Requires-Dist: networkx
